<class class="pizza_central_midfielder_passes" parent="match_rating_label" font="transparent" size="0" should_recolour="false" fixed_appearance_alignment="bottom" image_alignment="bottom">
	<list id="value_list">
		<record min_value="-1" max_value="37.43" appearance="mustermann/pizza/90/0" image_alignment="bottom" red_replacement="pizza_possess" colour="" hidden="false"/>
		<record min_value="37.43" max_value="43.11" appearance="mustermann/pizza/90/10" image_alignment="bottom" red_replacement="pizza_possess" colour="" hidden="false"/>
		<record min_value="43.11" max_value="47.63" appearance="mustermann/pizza/90/20" image_alignment="bottom" red_replacement="pizza_possess" colour="" hidden="false"/>
		<record min_value="47.63" max_value="51.50" appearance="mustermann/pizza/90/30" image_alignment="bottom" red_replacement="pizza_possess" colour="" hidden="false"/>
		<record min_value="51.50" max_value="55.44" appearance="mustermann/pizza/90/40" image_alignment="bottom" red_replacement="pizza_possess" colour="" hidden="false"/>
		<record min_value="55.44" max_value="59.16" appearance="mustermann/pizza/90/50" image_alignment="bottom" red_replacement="pizza_possess" colour="" hidden="false"/>
		<record min_value="59.16" max_value="63.47" appearance="mustermann/pizza/90/60" image_alignment="bottom" red_replacement="pizza_possess" colour="" hidden="false"/>
		<record min_value="63.47" max_value="68.74" appearance="mustermann/pizza/90/70" image_alignment="bottom" red_replacement="pizza_possess" colour="" hidden="false"/>
		<record min_value="68.74" max_value="75.44" appearance="mustermann/pizza/90/80" image_alignment="bottom" red_replacement="pizza_possess" colour="" hidden="false"/>
		<record min_value="75.44" max_value="106.02" appearance="mustermann/pizza/90/90" image_alignment="bottom" red_replacement="pizza_possess" colour="" hidden="false"/>
		<record min_value="106.02" max_value="1000" appearance="mustermann/pizza/90/100" image_alignment="bottom" red_replacement="pizza_possess" colour="" hidden="false"/>
	</list>
</class>